EQuadratic/__init__.py
EQuadratic/equadratic.py
EQuadratic-0.1.0.dist-info/METADATA
EQuadratic-0.1.0.dist-info/WHEEL
EQuadratic-0.1.0.dist-info/RECORD
