Metadata-Version: 2.1
Name: EQuadratic
Version: 0.1.0
Summary: Quadratic Equations made easy
Author: Siddhu Pendyala
License: MIT
Classifier: Intended Audience :: Developers
Classifier: License :: OSI Approved :: MIT License
Classifier: Programming Language :: Python
Classifier: Programming Language :: Python :: 3.9
Classifier: Operating System :: OS Independent
